fermy/CINAC.py
fermy/MTP.py
fermy/__init__.py
fermy/log.py
fermy/pandasfermy.py
fermy/plotlyfermy.py
fermy/driverslabtool/__init__.py
fermy/driverslabtool/errorslabtools.py
fermy/driverslabtool/probes.py
fermy/driverslabtool/pumps.py
fermy/driverslabtool/scales.py
fermy-0.5.9.dist-info/METADATA
fermy-0.5.9.dist-info/WHEEL
fermy-0.5.9.dist-info/top_level.txt
fermy-0.5.9.dist-info/RECORD
