Metadata-Version: 2.4
Name: fermy
Version: 0.5.9
Summary: Fermy is a toolkit to empower fermentation data analysis from Pandas DataFrame.
Home-page: https://gitlab.com/
Author: Nicolas Hardy
License: GPL-3.0-only
Keywords: fermentation,Biology,Pandas,data,growth rate,plots,control charts,multi-y axis,bioreactors
Classifier: Programming Language :: Python :: 3
Classifier: License :: OSI Approved :: GNU General Public License v3 (GPLv3)
Classifier: Operating System :: OS Independent
Requires-Python: >=3.7
Requires-Dist: et-xmlfile
Requires-Dist: numpy
Requires-Dist: openpyxl
Requires-Dist: pandas>=2.1.0
Requires-Dist: python-dateutil
Requires-Dist: pytz
Requires-Dist: six
Requires-Dist: plotly>=5.13.0
Provides-Extra: device
Requires-Dist: labjack-ljm; extra == "device"
Requires-Dist: pyserial; extra == "device"
Requires-Dist: minimalmodbus; extra == "device"
